setup.py
loq0/__init__.py
loq0/const.py
loq0/game.py
loq0.egg-info/PKG-INFO
loq0.egg-info/SOURCES.txt
loq0.egg-info/dependency_links.txt
loq0.egg-info/top_level.txt
loq0/state/__init__.py
loq0/state/print.py
loq0/state/state.py
loq0/state/actions/__init__.py
loq0/state/actions/move.py
loq0/state/actions/place.py
loq0/state/validate/blocked.py
loq0/state/validate/cross.py
loq0/state/validate/endable.py
loq0/state/validate/internal.py
loq0/state/validate/movable.py