Metadata-Version: 2.1
Name: loq0
Version: 0.0.7
Summary: League of Quoridor
Home-page: https://github.com/dastyinc/loq0
Author: seorii
Author-email: me@seorii.page
License: UNKNOWN
Platform: UNKNOWN
Classifier: Programming Language :: Python :: 3
Classifier: License :: OSI Approved :: MIT License
Classifier: Operating System :: OS Independent
Requires-Python: >=3.6
